hopic/__init__.py
hopic/__main__.py
hopic/binary_normalize.py
hopic/build.py
hopic/compat.py
hopic/config_reader.py
hopic/credentials.py
hopic/errors.py
hopic/execution.py
hopic/git_time.py
hopic/types.py
hopic/versioning.py
hopic/cli/__init__.py
hopic/cli/autocomplete.py
hopic/cli/build.py
hopic/cli/extensions.py
hopic/cli/global_obj.py
hopic/cli/main.py
hopic/cli/utils.py
hopic/template/__init__.py
hopic/template/utils.py
hopic-1.62.0.dist-info/LICENSE
hopic-1.62.0.dist-info/METADATA
hopic-1.62.0.dist-info/WHEEL
hopic-1.62.0.dist-info/entry_points.txt
hopic-1.62.0.dist-info/top_level.txt
hopic-1.62.0.dist-info/zip-safe
hopic-1.62.0.dist-info/RECORD
