Metadata-Version: 2.1
Name: hopic
Version: 1.62.0
Summary: In order to simplify the CI configuration we are switching away from the generic jenkins shared pipeline which is completely written in Groovy. Instead we are switching to the Hopic project which only has a minimal CI driver component written in Groovy with the rest written in Python. With Hopic local debugging is made significantly easier.
Home-page: https://github.com/tomtom-international/hopic
Author: TomTom N.V.
License: Apache License 2.0
Project-URL: Documentation, https://tomtom-international.github.io/hopic/
Project-URL: Change Log, https://tomtom-international.github.io/hopic/changes.html
Project-URL: Source Code, https://github.com/tomtom-international/hopic
Platform: UNKNOWN
Classifier: License :: OSI Approved :: Apache Software License
Requires-Python: >=3.6.5
Requires-Dist: Click (<8.0,>=7.0)
Requires-Dist: click-log
Requires-Dist: commisery (<1,>=0.5)
Requires-Dist: GitPython (!=3.1.15,<4,>=3)
Requires-Dist: python-dateutil
Requires-Dist: PyYAML
Requires-Dist: setuptools
Requires-Dist: typeguard (<2.11,<3,>=2.10)
Requires-Dist: importlib-metadata (>=3.6) ; python_version < "3.10.0b1"
Requires-Dist: typing-extensions (>=3.6.4) ; python_version < "3.8"
Provides-Extra: interactive
Requires-Dist: keyring (<22,>=21.5.0) ; extra == 'interactive'
Requires-Dist: netstruct (<2,>=1.1.2) ; extra == 'interactive'
